{
  "name": "@opswalrus/percolate",
  "version": "0.4.15",
  "exports": {
    ".": "./src/index.ts",
    "./array": "./src/array.ts",
    "./compactable": "./src/compactable.ts",
    "./enumerable": "./src/enumerable.ts",
    "./enumerator": "./src/enumerator.ts",
    "./file": "./src/file.ts",
    "./function": "./src/function.ts",
    "./map": "./src/map.ts",
    "./mappable": "./src/mappable.ts",
    "./object": "./src/object.ts",
    "./pipe": "./src/pipe.ts",
    "./protocol": "./src/protocol.ts",
    "./selectable": "./src/selectable.ts",
    "./set": "./src/set.ts",
    "./type": "./src/type.ts"
  }
}
